LICENSE
README.md
setup.py
gense/__init__.py
gense/gense.py
gense/synthesizer.py
gense.egg-info/PKG-INFO
gense.egg-info/SOURCES.txt
gense.egg-info/dependency_links.txt
gense.egg-info/requires.txt
gense.egg-info/top_level.txt